<?xml version="1.0" encoding="UTF-8"?>
<!DOCTYPE plist PUBLIC "-//Apple//DTD PLIST 1.0//EN" "http://www.apple.com/DTDs/PropertyList-1.0.dtd"/>

<plist version="1.0">
    <dict>
        <key>ROOT</key>
        <array>
            <dict>
                <key>id</key>
                <string>4007</string>
                <key>className</key>
                <string>PTModelAssetObstacle</string>
                <key>Name</key>
                <dict>
                    <key>value</key>
                    <string>1</string>
                </dict>
                <key>Collision Shape</key>
                <dict>
                    <key>id</key>
                    <string>4008</string>
                    <key>className</key>
                    <string>PTModelPolygon</string>
                    <key>Name</key>
                    <dict>
                        <key>value</key>
                        <string></string>
                    </dict>
                    <key>points</key>
                    <array>
                        <string>{-64.000000,-64.000000}</string>
                        <string>{64.000000,-64.000000}</string>
                        <string>{64.000000,64.000000}</string>
                        <string>{-64.000000,64.000000}</string>
                    </array>
                    <key>oneWayCollisionVector</key>
                    <string>{0.000000,0.000000}</string>
                    <key>shapeType</key>
                    <string>1</string>
                </dict>
            </dict>
            <dict>
                <key>id</key>
                <string>4131</string>
                <key>className</key>
                <string>PTModelAssetObstacle</string>
                <key>Name</key>
                <dict>
                    <key>value</key>
                    <string>Tree</string>
                </dict>
                <key>Collision Shape</key>
                <dict>
                    <key>id</key>
                    <string>4132</string>
                    <key>className</key>
                    <string>PTModelPolygon</string>
                    <key>Name</key>
                    <dict>
                        <key>value</key>
                        <string></string>
                    </dict>
                    <key>points</key>
                    <array>
                        <string>{-156.000000,-130.000000}</string>
                        <string>{157.000000,-130.000000}</string>
                        <string>{157.000000,130.000000}</string>
                        <string>{-156.000000,130.000000}</string>
                    </array>
                    <key>oneWayCollisionVector</key>
                    <string>{0.000000,0.000000}</string>
                    <key>shapeType</key>
                    <string>1</string>
                </dict>
            </dict>
            <dict>
                <key>id</key>
                <string>4471</string>
                <key>className</key>
                <string>PTModelAssetObstacle</string>
                <key>Name</key>
                <dict>
                    <key>value</key>
                    <string>Run (8)</string>
                </dict>
                <key>Collision Shape</key>
                <dict>
                    <key>id</key>
                    <string>4472</string>
                    <key>className</key>
                    <string>PTModelPolygon</string>
                    <key>Name</key>
                    <dict>
                        <key>value</key>
                        <string></string>
                    </dict>
                    <key>points</key>
                    <array>
                        <string>{-129.000000,-224.000000}</string>
                        <string>{163.000000,-224.000000}</string>
                        <string>{163.000000,223.000000}</string>
                        <string>{-129.000000,223.000000}</string>
                    </array>
                    <key>oneWayCollisionVector</key>
                    <string>{0.000000,0.000000}</string>
                    <key>shapeType</key>
                    <string>1</string>
                </dict>
            </dict>
            <dict>
                <key>id</key>
                <string>4686</string>
                <key>className</key>
                <string>PTModelAssetObstacle</string>
                <key>Name</key>
                <dict>
                    <key>value</key>
                    <string>SignArrow</string>
                </dict>
                <key>Collision Shape</key>
                <dict>
                    <key>id</key>
                    <string>4687</string>
                    <key>className</key>
                    <string>PTModelPolygon</string>
                    <key>Name</key>
                    <dict>
                        <key>value</key>
                        <string></string>
                    </dict>
                    <key>points</key>
                    <array>
                        <string>{-42.000000,-43.000000}</string>
                        <string>{42.000000,-43.000000}</string>
                        <string>{42.000000,44.000000}</string>
                        <string>{-42.000000,44.000000}</string>
                    </array>
                    <key>oneWayCollisionVector</key>
                    <string>{0.000000,0.000000}</string>
                    <key>shapeType</key>
                    <string>1</string>
                </dict>
            </dict>
            <dict>
                <key>id</key>
                <string>4847</string>
                <key>className</key>
                <string>PTModelAssetObstacle</string>
                <key>Name</key>
                <dict>
                    <key>value</key>
                    <string>image 17</string>
                </dict>
                <key>Collision Shape</key>
                <dict>
                    <key>id</key>
                    <string>4848</string>
                    <key>className</key>
                    <string>PTModelPolygon</string>
                    <key>Name</key>
                    <dict>
                        <key>value</key>
                        <string></string>
                    </dict>
                    <key>points</key>
                    <array>
                        <string>{-64.000000,-64.000000}</string>
                        <string>{64.000000,-64.000000}</string>
                        <string>{64.000000,64.000000}</string>
                        <string>{-64.000000,64.000000}</string>
                    </array>
                    <key>oneWayCollisionVector</key>
                    <string>{0.000000,0.000000}</string>
                    <key>shapeType</key>
                    <string>1</string>
                </dict>
            </dict>
            <dict>
                <key>id</key>
                <string>4871</string>
                <key>className</key>
                <string>PTModelAssetObstacle</string>
                <key>Name</key>
                <dict>
                    <key>value</key>
                    <string>boat png</string>
                </dict>
                <key>Collision Shape</key>
                <dict>
                    <key>id</key>
                    <string>4872</string>
                    <key>className</key>
                    <string>PTModelPolygon</string>
                    <key>Name</key>
                    <dict>
                        <key>value</key>
                        <string></string>
                    </dict>
                    <key>points</key>
                    <array>
                        <string>{-511.000000,-286.000000}</string>
                        <string>{514.000000,-286.000000}</string>
                        <string>{514.000000,578.000000}</string>
                        <string>{-511.000000,578.000000}</string>
                    </array>
                    <key>oneWayCollisionVector</key>
                    <string>{0.000000,0.000000}</string>
                    <key>shapeType</key>
                    <string>1</string>
                </dict>
            </dict>
            <dict>
                <key>id</key>
                <string>5359</string>
                <key>className</key>
                <string>PTModelAssetObstacle</string>
                <key>Name</key>
                <dict>
                    <key>value</key>
                    <string>Cactus (1)</string>
                </dict>
                <key>Collision Shape</key>
                <dict>
                    <key>id</key>
                    <string>5360</string>
                    <key>className</key>
                    <string>PTModelPolygon</string>
                    <key>Name</key>
                    <dict>
                        <key>value</key>
                        <string></string>
                    </dict>
                    <key>points</key>
                    <array>
                        <string>{-54.000000,-55.000000}</string>
                        <string>{54.000000,-55.000000}</string>
                        <string>{54.000000,56.000000}</string>
                        <string>{-54.000000,56.000000}</string>
                    </array>
                    <key>oneWayCollisionVector</key>
                    <string>{0.000000,0.000000}</string>
                    <key>shapeType</key>
                    <string>1</string>
                </dict>
            </dict>
            <dict>
                <key>id</key>
                <string>5548</string>
                <key>className</key>
                <string>PTModelAssetObstacle</string>
                <key>Name</key>
                <dict>
                    <key>value</key>
                    <string>Bush (1)</string>
                </dict>
                <key>Collision Shape</key>
                <dict>
                    <key>id</key>
                    <string>5549</string>
                    <key>className</key>
                    <string>PTModelPolygon</string>
                    <key>Name</key>
                    <dict>
                        <key>value</key>
                        <string></string>
                    </dict>
                    <key>points</key>
                    <array>
                        <string>{-72.000000,-44.000000}</string>
                        <string>{73.000000,-44.000000}</string>
                        <string>{73.000000,44.000000}</string>
                        <string>{-72.000000,44.000000}</string>
                    </array>
                    <key>oneWayCollisionVector</key>
                    <string>{0.000000,0.000000}</string>
                    <key>shapeType</key>
                    <string>1</string>
                </dict>
            </dict>
            <dict>
                <key>id</key>
                <string>5761</string>
                <key>className</key>
                <string>PTModelAssetObstacle</string>
                <key>Name</key>
                <dict>
                    <key>value</key>
                    <string>Skeleton</string>
                </dict>
                <key>Collision Shape</key>
                <dict>
                    <key>id</key>
                    <string>5762</string>
                    <key>className</key>
                    <string>PTModelPolygon</string>
                    <key>Name</key>
                    <dict>
                        <key>value</key>
                        <string></string>
                    </dict>
                    <key>points</key>
                    <array>
                        <string>{-75.000000,-25.000000}</string>
                        <string>{75.000000,-25.000000}</string>
                        <string>{75.000000,26.000000}</string>
                        <string>{-75.000000,26.000000}</string>
                    </array>
                    <key>oneWayCollisionVector</key>
                    <string>{0.000000,0.000000}</string>
                    <key>shapeType</key>
                    <string>1</string>
                </dict>
            </dict>
        </array>
    </dict>
</plist>
